sameproject/__init__.py
sameproject/backends/.funcignore
sameproject/backends/README.md
sameproject/backends/__init__.py
sameproject/backends/aml/__init__.py
sameproject/backends/aml/deploy.py
sameproject/backends/aml/render.py
sameproject/backends/common/__init__.py
sameproject/backends/common/code_executor.py
sameproject/backends/common/exception_utils.py
sameproject/backends/common/http_utils.py
sameproject/backends/common/serialization_utils.py
sameproject/backends/durable_functions/.funcignore
sameproject/backends/durable_functions/.vscode/extensions.json
sameproject/backends/durable_functions/.vscode/launch.json
sameproject/backends/durable_functions/.vscode/settings.json
sameproject/backends/durable_functions/.vscode/tasks.json
sameproject/backends/durable_functions/__init__.py
sameproject/backends/durable_functions/__main__.py
sameproject/backends/durable_functions/constants.py
sameproject/backends/durable_functions/execute_step/__init__.py
sameproject/backends/durable_functions/execute_step/context.py
sameproject/backends/durable_functions/execute_step/execute_step.py
sameproject/backends/durable_functions/execute_step/execution_environment.py
sameproject/backends/durable_functions/execute_step/function.json
sameproject/backends/durable_functions/execute_steps_workflow/__init__.py
sameproject/backends/durable_functions/execute_steps_workflow/context.py
sameproject/backends/durable_functions/execute_steps_workflow/execute_steps_workflow.py
sameproject/backends/durable_functions/execute_steps_workflow/function.json
sameproject/backends/durable_functions/host.json
sameproject/backends/durable_functions/proxies.json
sameproject/backends/durable_functions/requirements.txt
sameproject/backends/durable_functions/start_steps_workflow/__init__.py
sameproject/backends/durable_functions/start_steps_workflow/context.py
sameproject/backends/durable_functions/start_steps_workflow/function.json
sameproject-0.1.16.dist-info/entry_points.txt
sameproject-0.1.16.dist-info/LICENSE
sameproject-0.1.16.dist-info/WHEEL
sameproject-0.1.16.dist-info/METADATA
sameproject-0.1.16.dist-info/RECORD
